zomboid_rcon/__init__.py
zomboid_rcon/zomboid_rcon.py
zomboid_rcon/source/CommandResult.py
zomboid_rcon/source/RconClient.py
zomboid_rcon/source/__init__.py
zomboid_rcon-1.2.0.dist-info/licenses/LICENSE
zomboid_rcon-1.2.0.dist-info/METADATA
zomboid_rcon-1.2.0.dist-info/WHEEL
zomboid_rcon-1.2.0.dist-info/top_level.txt
zomboid_rcon-1.2.0.dist-info/RECORD
