Metadata-Version: 2.4
Name: zomboid_rcon
Version: 1.2.0
Summary: Python class for interacting with Project Zomboid servers using RCON 
Author-email: Jack Whitworth <jack@jackwhitworth.com>
License: GNU GENERAL PUBLIC LICENSE
Project-URL: Homepage, https://github.com/jmwhitworth/zomboid_rcon
Keywords: project-zomboid,rcon,project-zomboid-rcon
Classifier: Development Status :: 5 - Production/Stable
Classifier: Intended Audience :: Developers
Classifier: Topic :: Software Development :: Build Tools
Classifier: License :: OSI Approved :: GNU General Public License (GPL)
Classifier: Programming Language :: Python :: 3.10
Classifier: Programming Language :: Python :: 3.11
Classifier: Programming Language :: Python :: 3.12
Classifier: Programming Language :: Python :: 3.13
Classifier: Programming Language :: Python :: 3.14
Requires-Python: >=3.10
License-File: LICENSE
Requires-Dist: rcon>=2.4.9
Requires-Dist: timeout_decorator>=0.5.0
Provides-Extra: dev
Dynamic: license-file
